kfw/__init__.py
kfw/callbacks.py
kfw/losses.py
kfw/metrics.py
kfw-0.0.1a9.dist-info/LICENSE
kfw-0.0.1a9.dist-info/METADATA
kfw-0.0.1a9.dist-info/WHEEL
kfw-0.0.1a9.dist-info/top_level.txt
kfw-0.0.1a9.dist-info/RECORD
