Metadata-Version: 2.1
Name: kfw
Version: 0.0.1a9
Summary: keras framework wrapper
Home-page: https://gitlab.com/hebinhao1993/kfw
Author: hebinhao
Author-email: hebinhao1993@outlook.com
License: UNKNOWN
Platform: UNKNOWN
Classifier: Programming Language :: Python :: 3
Classifier: License :: OSI Approved :: GNU General Public License v3 (GPLv3)
Classifier: Operating System :: OS Independent
Requires-Dist: keras
